snakemake_storage_plugin_nersc/__init__.py
snakemake_storage_plugin_nersc-0.1.3.dist-info/METADATA
snakemake_storage_plugin_nersc-0.1.3.dist-info/WHEEL
snakemake_storage_plugin_nersc-0.1.3.dist-info/entry_points.txt
snakemake_storage_plugin_nersc-0.1.3.dist-info/RECORD
