Metadata-Version: 2.4
Name: snakemake-storage-plugin-nersc
Version: 0.1.3
Summary: Snakemake plugin to interact with the NERSC filesystem
Project-URL: Repository, https://github.com/legend-exp/snakemake-storage-plugin-nersc
Project-URL: Documentation, https://snakemake.github.io/snakemake-plugin-catalog/plugins/storage/nersc.html
Author-email: Luigi Pertoldi <luigi.pertoldi@protonmail.com>
Maintainer: The LEGEND Collaboration
Requires-Python: <4.0,>=3.11
Requires-Dist: snakemake-interface-common<2,>=1.22.0
Requires-Dist: snakemake-interface-storage-plugins<5,>=4.3.2
